{"_id":{"$oid":"652986933813c06959ff4296"},"name":"Daily Updates","description":"Daily Updates","tagId":"a570ff82-2b86-4f14-a7d9-b9ad955c0930","__v":0}
{"_id":{"$oid":"6529870c3813c06959ff429a"},"name":"Java","description":"Java","tagId":"2d026c79-9540-4016-bd4c-2782fe88d843","__v":0}
{"_id":{"$oid":"652987213813c06959ff429e"},"name":"Weekly Consolidated Updates","description":"Weekly Consolidated Updates","tagId":"e07012d9-d400-4074-80e5-32b167bedcb4","__v":0}
{"_id":{"$oid":"6529875e3813c06959ff42a2"},"name":"Personal Updates","description":"Personal Updates","tagId":"83383967-6398-4f93-86e3-a9d29590c012","__v":0}
{"_id":{"$oid":"652987943813c06959ff42a6"},"name":"Office Updates","description":"Office Updates","tagId":"34e2644f-e8a3-46bf-9408-6089e4e10bd4","__v":0}
{"_id":{"$oid":"652a62f0830b26bf2f667951"},"name":"Tutorials","description":"Tutorials","tagId":"7f3f707f-7ada-4d2c-9e99-b8176138e860","__v":0}
{"_id":{"$oid":"652a6557830b26bf2f66795e"},"name":"My Matrimonial Issue Tracker","description":"My Matrimonial Issue Tracker","tagId":"8542232f-c36e-494e-a0ce-287b6604380e","__v":0}
{"_id":{"$oid":"6543853bce2b04477b9887a0"},"name":"My Targets","description":"My Targets","tagId":"bc913f1a-23b3-4d15-8e95-6101c29ce614","__v":0}
{"_id":{"$oid":"6564c49a4a989b7c6b18930b"},"name":"Process Establishment","description":"Process Establishment","tagId":"28010c8e-eed7-4304-8a0a-413e445a0cc6","__v":0}
{"_id":{"$oid":"656822c7d6dac727461c2581"},"name":"Planning","description":"Planning","tagId":"57c5a673-3708-409d-aaa8-7baa1ef1a3ae","__v":0}
{"_id":{"$oid":"65684ec7d6dac727461c25d9"},"name":"Monthly Expenses","description":"Monthly Expenses","tagId":"e13dba57-e079-49f6-97fa-566c1684b7c0","__v":0}
